afl_tables/__init__.py
afl_tables/cli.py
afl_tables-0.0.2.dist-info/LICENSE
afl_tables-0.0.2.dist-info/METADATA
afl_tables-0.0.2.dist-info/WHEEL
afl_tables-0.0.2.dist-info/entry_points.txt
afl_tables-0.0.2.dist-info/top_level.txt
afl_tables-0.0.2.dist-info/RECORD
