Metadata-Version: 2.1
Name: afl-tables
Version: 0.0.2
Summary: UNKNOWN
Home-page: UNKNOWN
Author: Michael Milton
Author-email: michael.r.milton@gmail.com
License: GPLv3
Platform: UNKNOWN
Requires-Dist: beautifulsoup4
Requires-Dist: requests
Requires-Dist: html5lib
Requires-Dist: pytz
Provides-Extra: dev
Requires-Dist: pytest ; extra == 'dev'
Requires-Dist: sphinx ; extra == 'dev'
Requires-Dist: recommonmark ; extra == 'dev'
